flask_magql/__init__.py
flask_magql/_extension.py
flask_magql/_files.py
flask_magql/_views.py
flask_magql/py.typed
flask_magql/templates/magql/conveyor.html
flask_magql/templates/magql/graphiql.html
flask_magql-1.1.1.dist-info/LICENSE.txt
flask_magql-1.1.1.dist-info/WHEEL
flask_magql-1.1.1.dist-info/METADATA
flask_magql-1.1.1.dist-info/RECORD
