Metadata-Version: 2.1
Name: flask-magql
Version: 1.1.1
Summary: Serve a Magql GraphQL API with Flask.
Author: David Lord
Requires-Python: >=3.10
Requires-Dist: magql>=1.0.1
Requires-Dist: flask>=2.3
Project-URL: Changes, https://flask-magql.autoinvent.dev/page/changes/
Project-URL: Documentation, https://flask-magql.autoinvent.dev
Project-URL: Source, https://github.com/autoinvent/flask-magql/
